README.md
setup.py
searchoffer/__init__.py
searchoffer/searchoffer.py
searchoffer.egg-info/PKG-INFO
searchoffer.egg-info/SOURCES.txt
searchoffer.egg-info/dependency_links.txt
searchoffer.egg-info/requires.txt
searchoffer.egg-info/top_level.txt