Metadata-Version: 2.1
Name: searchoffer
Version: 0.0.3
Summary: Python library suggestqueries google api
Home-page: https://github.com/mahekan/searchoffer
Author: ayaz abdi
Author-email: mayazabdi@gmail.com
License: UNKNOWN
Platform: UNKNOWN
Classifier: Programming Language :: Python :: 3.8
Classifier: License :: OSI Approved :: GNU General Public License v3 (GPLv3)
